<?xml version="1.0" encoding="UTF-8"?>
<objects serializationModel="Studio.02.02.00">
	<object class="Event" id="{9b061b8f-e51f-4bde-b75a-8ef501b75332}">
		<property name="name">
			<value>WaterfallEvent</value>
		</property>
		<property name="outputFormat">
			<value>2</value>
		</property>
		<relationship name="folder">
			<destination>{c3456d2f-1577-46f7-8d9f-c54e1bbb538d}</destination>
		</relationship>
		<relationship name="mixer">
			<destination>{d7b42c5d-9e59-48e0-af26-432c3a687733}</destination>
		</relationship>
		<relationship name="masterTrack">
			<destination>{b07d104a-68d9-4697-ab24-4d4dd064504d}</destination>
		</relationship>
		<relationship name="mixerInput">
			<destination>{e273c369-498d-4d9b-b5a9-0936284de24d}</destination>
		</relationship>
		<relationship name="automatableProperties">
			<destination>{78303b04-8fac-4b02-8ad5-c33fb2cb1c64}</destination>
		</relationship>
		<relationship name="markerTracks">
			<destination>{de0ffeaf-5d64-4c96-8862-e1d057407dcf}</destination>
		</relationship>
		<relationship name="groupTracks">
			<destination>{5d8e1ce0-a4fe-4358-bae0-452db8ecd8d3}</destination>
		</relationship>
		<relationship name="timeline">
			<destination>{3a629df2-4db0-4c19-9db9-0103f8c135fb}</destination>
		</relationship>
		<relationship name="parameters">
			<destination>{e6eb1fd4-fb9d-4515-abc0-c8e94513bea0}</destination>
		</relationship>
		<relationship name="banks">
			<destination>{32dcd399-f0e3-4f1c-92ba-47e14905ffcf}</destination>
		</relationship>
	</object>
	<object class="EventMixer" id="{d7b42c5d-9e59-48e0-af26-432c3a687733}">
		<relationship name="masterBus">
			<destination>{de61c906-7d0a-4eae-a4ca-caf11c91c8ef}</destination>
		</relationship>
	</object>
	<object class="MasterTrack" id="{b07d104a-68d9-4697-ab24-4d4dd064504d}">
		<relationship name="automationTracks">
			<destination>{00a6dc6a-32f5-4523-b3fb-6fa291d8733d}</destination>
		</relationship>
		<relationship name="mixerGroup">
			<destination>{de61c906-7d0a-4eae-a4ca-caf11c91c8ef}</destination>
		</relationship>
	</object>
	<object class="MixerInput" id="{e273c369-498d-4d9b-b5a9-0936284de24d}">
		<relationship name="effectChain">
			<destination>{f778260c-b8b8-4083-9f55-b7911e1aa691}</destination>
		</relationship>
		<relationship name="panner">
			<destination>{5f076da3-9470-4485-8981-c243b657c24d}</destination>
		</relationship>
		<relationship name="output">
			<destination>{c0ac66b5-64a1-4e08-9d3b-9fdf14fa89c9}</destination>
		</relationship>
	</object>
	<object class="EventAutomatableProperties" id="{78303b04-8fac-4b02-8ad5-c33fb2cb1c64}" />
	<object class="MarkerTrack" id="{de0ffeaf-5d64-4c96-8862-e1d057407dcf}" />
	<object class="GroupTrack" id="{5d8e1ce0-a4fe-4358-bae0-452db8ecd8d3}">
		<relationship name="modules">
			<destination>{fe398cc4-e6ac-49f8-85de-af5eaa103ea2}</destination>
			<destination>{a930463b-3e41-41ca-8d8e-1fe97edaaf1f}</destination>
		</relationship>
		<relationship name="mixerGroup">
			<destination>{eb214a5f-eee0-4690-bda4-ca1db1b4e93a}</destination>
		</relationship>
	</object>
	<object class="Timeline" id="{3a629df2-4db0-4c19-9db9-0103f8c135fb}" />
	<object class="ParameterProxy" id="{e6eb1fd4-fb9d-4515-abc0-c8e94513bea0}">
		<relationship name="modules">
			<destination>{fe398cc4-e6ac-49f8-85de-af5eaa103ea2}</destination>
			<destination>{a930463b-3e41-41ca-8d8e-1fe97edaaf1f}</destination>
		</relationship>
		<relationship name="preset">
			<destination>{720dd393-71a9-4e43-bef5-e1aeed1560d8}</destination>
		</relationship>
	</object>
	<object class="EventMixerMaster" id="{de61c906-7d0a-4eae-a4ca-caf11c91c8ef}">
		<relationship name="automators">
			<destination>{f6e0f3da-24d5-49c3-9577-65a9ef51676a}</destination>
		</relationship>
		<relationship name="effectChain">
			<destination>{92c23b62-7a82-4373-81a7-d5ad4791d63a}</destination>
		</relationship>
		<relationship name="panner">
			<destination>{6cc9b2db-6d6a-4f52-a9e9-cce30c301d7c}</destination>
		</relationship>
		<relationship name="mixer">
			<destination>{d7b42c5d-9e59-48e0-af26-432c3a687733}</destination>
		</relationship>
	</object>
	<object class="AutomationTrack" id="{00a6dc6a-32f5-4523-b3fb-6fa291d8733d}">
		<relationship name="automator">
			<destination>{f6e0f3da-24d5-49c3-9577-65a9ef51676a}</destination>
		</relationship>
	</object>
	<object class="MixerBusEffectChain" id="{f778260c-b8b8-4083-9f55-b7911e1aa691}">
		<relationship name="effects">
			<destination>{3d55d3af-d240-4df0-9dcb-6b43fe1d2e79}</destination>
		</relationship>
	</object>
	<object class="MixerBusPanner" id="{5f076da3-9470-4485-8981-c243b657c24d}" />
	<object class="SingleSound" id="{fe398cc4-e6ac-49f8-85de-af5eaa103ea2}">
		<property name="start">
			<value>0.17000000000000001</value>
		</property>
		<property name="length">
			<value>0.83000000000000029</value>
		</property>
		<property name="looping">
			<value>true</value>
		</property>
		<relationship name="fadeInCurve">
			<destination>{811786e9-6beb-4f7c-87ca-ed21621ecaa8}</destination>
		</relationship>
		<relationship name="audioFile">
			<destination>{1eecaaf0-ef81-4cd1-b488-9a8ee7441976}</destination>
		</relationship>
	</object>
	<object class="SingleSound" id="{a930463b-3e41-41ca-8d8e-1fe97edaaf1f}">
		<property name="length">
			<value>0.93000000000000005</value>
		</property>
		<property name="looping">
			<value>true</value>
		</property>
		<relationship name="fadeOutCurve">
			<destination>{4f312e90-b6ce-4dc1-a8c6-6ed6ff24fff2}</destination>
		</relationship>
		<relationship name="audioFile">
			<destination>{61da96b8-3b56-41c5-b8a3-3c86f2f1693c}</destination>
		</relationship>
	</object>
	<object class="EventMixerGroup" id="{eb214a5f-eee0-4690-bda4-ca1db1b4e93a}">
		<property name="volume">
			<value>-6</value>
		</property>
		<property name="name">
			<value>Audio 1</value>
		</property>
		<relationship name="effectChain">
			<destination>{aa49f54b-b4ae-4d5f-ad16-2f14c4beab6f}</destination>
		</relationship>
		<relationship name="panner">
			<destination>{167f6acb-df2b-4e49-8a4d-a9fac7e8c2aa}</destination>
		</relationship>
		<relationship name="output">
			<destination>{de61c906-7d0a-4eae-a4ca-caf11c91c8ef}</destination>
		</relationship>
	</object>
	<object class="Automator" id="{f6e0f3da-24d5-49c3-9577-65a9ef51676a}">
		<property name="nameOfPropertyBeingAutomated">
			<value>volume</value>
		</property>
		<relationship name="automationCurves">
			<destination>{9c0018ea-5746-489e-80fd-3d70a9d47b9f}</destination>
		</relationship>
	</object>
	<object class="MixerBusEffectChain" id="{92c23b62-7a82-4373-81a7-d5ad4791d63a}">
		<relationship name="effects">
			<destination>{f3e92825-2f07-49b4-9738-2fe789e1e487}</destination>
			<destination>{dc7f6263-c0f6-4604-950e-083b8f961330}</destination>
		</relationship>
	</object>
	<object class="MixerBusPanner" id="{6cc9b2db-6d6a-4f52-a9e9-cce30c301d7c}" />
	<object class="MixerBusFader" id="{3d55d3af-d240-4df0-9dcb-6b43fe1d2e79}" />
	<object class="FadeCurve" id="{811786e9-6beb-4f7c-87ca-ed21621ecaa8}">
		<relationship name="startPoint">
			<destination>{bf42984e-1454-4226-8629-33de2e8d0752}</destination>
		</relationship>
		<relationship name="endPoint">
			<destination>{8dcbbccf-6dc0-40f9-b9ca-9bca63d64dc1}</destination>
		</relationship>
	</object>
	<object class="FadeCurve" id="{4f312e90-b6ce-4dc1-a8c6-6ed6ff24fff2}">
		<relationship name="startPoint">
			<destination>{637dcf9c-340b-4e10-a783-12d647b20c27}</destination>
		</relationship>
		<relationship name="endPoint">
			<destination>{6e6e50ea-a915-456a-9a1b-7fd69869d3ac}</destination>
		</relationship>
	</object>
	<object class="MixerBusEffectChain" id="{aa49f54b-b4ae-4d5f-ad16-2f14c4beab6f}">
		<relationship name="effects">
			<destination>{5e281f72-7c5e-4d85-a2f7-af2103b63278}</destination>
		</relationship>
	</object>
	<object class="MixerBusPanner" id="{167f6acb-df2b-4e49-8a4d-a9fac7e8c2aa}" />
	<object class="AutomationCurve" id="{9c0018ea-5746-489e-80fd-3d70a9d47b9f}">
		<relationship name="parameter">
			<destination>{720dd393-71a9-4e43-bef5-e1aeed1560d8}</destination>
		</relationship>
		<relationship name="automationPoints">
			<destination>{38ebc270-47d7-4063-a723-145e95155b5d}</destination>
			<destination>{c2e410b1-dcb3-4d7c-ac31-58ef75973cc6}</destination>
		</relationship>
	</object>
	<object class="MixerBusFader" id="{f3e92825-2f07-49b4-9738-2fe789e1e487}" />
	<object class="SpatialiserEffect" id="{dc7f6263-c0f6-4604-950e-083b8f961330}">
		<property name="distanceRolloffType">
			<value>1</value>
		</property>
		<property name="maximumDistance">
			<value>300</value>
		</property>
		<property name="overrideRange">
			<value>true</value>
		</property>
	</object>
	<object class="AutomationPoint" id="{bf42984e-1454-4226-8629-33de2e8d0752}">
		<property name="position">
			<value>0.17000000000000001</value>
		</property>
		<property name="value">
			<value>0</value>
		</property>
		<property name="curveShape">
			<value>-0.2547189</value>
		</property>
	</object>
	<object class="AutomationPoint" id="{8dcbbccf-6dc0-40f9-b9ca-9bca63d64dc1}">
		<property name="position">
			<value>0.84999999999999998</value>
		</property>
		<property name="value">
			<value>1</value>
		</property>
	</object>
	<object class="AutomationPoint" id="{637dcf9c-340b-4e10-a783-12d647b20c27}">
		<property name="position">
			<value>0.12000000000000005</value>
		</property>
		<property name="value">
			<value>1</value>
		</property>
		<property name="curveShape">
			<value>0.00914411712</value>
		</property>
	</object>
	<object class="AutomationPoint" id="{6e6e50ea-a915-456a-9a1b-7fd69869d3ac}">
		<property name="position">
			<value>0.93000000000000005</value>
		</property>
		<property name="value">
			<value>0</value>
		</property>
	</object>
	<object class="MixerBusFader" id="{5e281f72-7c5e-4d85-a2f7-af2103b63278}" />
	<object class="AutomationPoint" id="{38ebc270-47d7-4063-a723-145e95155b5d}">
		<property name="position">
			<value>0</value>
		</property>
		<property name="value">
			<value>-3</value>
		</property>
	</object>
	<object class="AutomationPoint" id="{c2e410b1-dcb3-4d7c-ac31-58ef75973cc6}">
		<property name="position">
			<value>1</value>
		</property>
		<property name="value">
			<value>-7</value>
		</property>
	</object>
</objects>
